{"analyzed_count":2,"detailed_report":"# Clinical Report: Amlodipine and Lisinopril Combination\n## Introduction\nThe combination of Amlodipine, a calcium channel blocker, and Lisinopril, an angiotensin-converting enzyme (ACE) inhibitor, is commonly used to manage hypertension and heart failure. However, this combination may increase the risk of adverse effects, particularly life-threatening hyperkalemia and acute kidney injury.\n## Mechanism of Interaction\nAmlodipine can increase potassium levels in the body by reducing potassium excretion, while Lisinopril can increase potassium levels by reducing aldosterone levels, leading to a decrease in potassium excretion. This synergistic effect can lead to a potentially toxic buildup of potassium in the body.\n## Risks and Complications\nThe combination of Amlodipine and Lisinopril may increase the risk of life-threatening hyperkalemia, acute kidney injury, and anaphylaxis. Hyperkalemia can lead to cardiac arrhythmias, muscle weakness, and respiratory failure, while acute kidney injury can lead to a buildup of waste products in the body, potentially resulting in serious complications.\n## Alternatives and Mitigation Strategies\nSafer alternatives, such as Losartan or Candesartan, may be considered to minimize the risks associated with this combination. Regular monitoring of potassium levels and kidney function can help mitigate potential complications. Healthcare providers should carefully weigh the benefits and risks of this combination before prescribing and consider alternative treatment options.\n## Actionable Advice\nPatients taking Amlodipine and Lisinopril should be closely monitored for signs of hyperkalemia and acute kidney injury, including muscle weakness, fatigue, and changes in urine output. Patients should also be advised to report any symptoms promptly to their healthcare provider. Additionally, patients should be educated on the importance of regular monitoring and the potential risks associated with this combination.","medium_analysis":"The combination of Amlodipine and Lisinopril may increase the risk of adverse effects, particularly life-threatening hyperkalemia and acute kidney injury. This is because both medications can increase potassium levels in the body, leading to a potentially toxic buildup. Safer alternatives, such as Losartan or Candesartan, may be considered to minimize these risks. Additionally, regular monitoring of potassium levels and kidney function can help mitigate potential complications. Healthcare providers should carefully weigh the benefits and risks of this combination before prescribing.","severity":"Analyzed","short_analysis":"Hyperkalemia","status":"success"}
